{"exposureTime":0.003,"shutterSpeed":8.6439,"height":853,"shutterSpeedFormatted":"8.64 EV (1\/400 sec.)","keywords":[{"name":"2018","url":"content\/keywords\/2018.json"},{"name":"FR","url":"content\/keywords\/FR.json"},{"name":"France","url":"content\/keywords\/France.json"},{"url":"content\/keywords\/Paris.json","name":"Paris"},{"name":"Île-de-France","url":"content\/keywords\/Île-de-France.json"}],"fNumberFormatted":"f\/7.1","scaledPhotos":[{"url":"content\/root\/2018\/2018-06-02_Paris\/20180603-150706-IMG_7922_1200.jpg","maxResolution":1200},{"url":"content\/root\/2018\/2018-06-02_Paris\/20180603-150706-IMG_7922_992.jpg","maxResolution":992},{"maxResolution":768,"url":"content\/root\/2018\/2018-06-02_Paris\/20180603-150706-IMG_7922_768.jpg"},{"url":"content\/root\/2018\/2018-06-02_Paris\/20180603-150706-IMG_7922_576.jpg","maxResolution":576},{"maxResolution":340,"url":"content\/root\/2018\/2018-06-02_Paris\/20180603-150706-IMG_7922_340.jpg"},{"maxResolution":220,"url":"content\/root\/2018\/2018-06-02_Paris\/20180603-150706-IMG_7922_220.jpg"},{"url":"content\/root\/2018\/2018-06-02_Paris\/20180603-150706-IMG_7922_180.jpg","maxResolution":180}],"originalImageURL":"content\/root\/2018\/2018-06-02_Paris\/20180603-150706-IMG_7922_original.jpg","originalImagePath":"album\/2018\/2018-06-02 Paris\/20180603-150706-IMG_7922.jpg","gps":{"longitude":2.337102777777778,"latitude":48.84565,"altitude":43},"url":"content\/root\/2018\/2018-06-02_Paris\/20180603-150706-IMG_7922.json","location":{"state":"Île-de-France","city":"Paris","locationName":"France","locationCode":"FR"},"owner":"Kristoffer Andreas Dalby","copyright":"Photographer: Kristoffer Andreas Dalby","people":[],"fNumber":7.1,"orientation":"landscape","apertureFormatted":"5.66 EV (f\/7.1)","previous":"content\/root\/2018\/2018-06-02_Paris\/20180602-173727-IMG_7893.json","aperture":5.6556,"lensModel":"EF50mm f\/1.4 USM","focalLengthFormatted":"50.0 mm","meteringModeFormatted":"Pattern","name":"20180603-150706-IMG_7922","cameraMake":"Canon","next":"content\/root\/2018\/2018-06-02_Paris\/20180603-181008-IMG_7954.json","focalLength":50,"dateTime":"2018-06-03T13:07:06Z","parents":[{"name":"root","url":"content\/root\/index.json"},{"url":"content\/root\/2018\/index.json","name":"2018"},{"url":"content\/root\/2018\/2018-06-02_Paris\/index.json","name":"2018-06-02 Paris"}],"width":1280,"modifiedDate":"2022-12-20T17:37:07Z","exposureTimeFormatted":"1\/400 sec.","meteringMode":5,"isoSpeed":[100],"cameraModel":"Canon EOS 5D Mark II"}